{
  "book": "jdt",
  "chapter": 8,
  "verses": [
    {
      "verse": 1,
      "text": "उस समय जूडिथ ने यह सुना, जो मरारी का पुत्रा, और मरारी का पोता, और यूसुफ का पोता, और एलीएल का पोता, और हनन्याह का पुत्रा, यह गेर्श का पुत्रा, यह गेर्श का पुत्रा, यह गेहर का पुत्रा, यह एलीह का पुत्रा, यह एलीह का पुत्रा, यह एलीएल का पुत्रा, यह एलीएल का पुत्रा था।"
    },
    {
      "verse": 2,
      "text": "और उसके गोत्रा और कुटुम्ब का पति था, जो जव की कटनी के समय मर गया था।"
    },
    {
      "verse": 3,
      "text": "जब वह खेत में पूलियों की रक्षा कर रहा था, तब उसके सिर पर गर्मी छा गई, और वह अपने बिछौने पर पड़ा हुआ बेतहमिया नगर में मर गया; और उसको दोथैम और बालमो के बीच मैदान में मिट्टी दी गई।"
    },
    {
      "verse": 4,
      "text": "इसलिए जूडिथ उसके घर में तीन साल और चार महीने की एक विधवा थी ।"
    },
    {
      "verse": 5,
      "text": "और उस ने अपने घर की छत पर अपना तम्बू बनाया, और अपनी कमर पर टाट बान्धा, और अपनी विधवा के वस्त्र फाड़े।"
    },
    {
      "verse": 6,
      "text": "और उस ने अपने विधवापन के सारे दिन, अर्थात् विश्रामदिनों और नये चांद के दिनों, और नये चांद के दिनों, और इस्राएल के घराने के नियत समयों और नियत समयों के दिनों में उपवास किया।"
    },
    {
      "verse": 7,
      "text": "और वह देखने में सुन्दर थी, और उसके पति के मन में सोना, चान्दी, दास- दासी, गाय- बैल, और भूमि रह गई थी; और वह उन पर बैठी रही।"
    },
    {
      "verse": 8,
      "text": "और जब वह परमेश्वर का बहुत भय मानती थी, तब किसी ने उसे बुरा वचन नहीं दिया था।"
    },
    {
      "verse": 9,
      "text": "जब उस ने हाकिम के विरूद्ध लोगों की बुरी बातें सुनी, तब जल की घटी में पड़कर नाश हो गए; क्योंकि इन सब वचनों को हम ने सुना था, और उस ने नगर को पांच दिन के बाद अश्शूरियों के हाथ सौंप देने की शपथ खाई थी।"
    },
    {
      "verse": 10,
      "text": "तब उस ने उस स्त्री को बुलवा भेजा, कि जो कुछ उसके पास था, उस की सरकार उसके पास ओब्रीस, सिब्रीस, और गेब्रीस नाम नगर के प्राचीन लोगों को बुला ले जाए।"
    },
    {
      "verse": 11,
      "text": "तब उन्हों ने उसके पास आकर कहा, हे बेतगाती के निवासियों के हाकिमों, मेरी सुनो; क्योंकि जो बातें तुम लोगों ने आज तक लोगों के साम्हने कही हैं, वे इस बात पर ठीक नहीं हैं, जो तुम ने परमेश्वर और तुम दोनों के बीच में कही हैं, और जब तक इन दिनों में हमारे शत्रुओं को छुड़ाने का वचन न मिले, तब तक तुम मेरी सुनो।"
    },
    {
      "verse": 12,
      "text": "और तुम जो आज परमेश्वर की परीक्षा करते हो, और मनुष्यों के बीच परमेश्वर के साम्हने खड़े रहते हो?"
    },
    {
      "verse": 13,
      "text": "और अब सर्वशक्तिमान प्रभु की परीक्षा करो, पर तुम को किसी बात का ज्ञान न होगा।"
    },
    {
      "verse": 14,
      "text": "क्योंकि तुम मनुष्य के मन की गहराई को न पा सकते हो, और जो बातें वह समझता है, उन्हें तुम नहीं पा सकते; फिर जिस ने इन सब वस्तुओं को बनाया, उस ने परमेश्वर को क्यों ढूंढ़- ढांढ़ किया, और उसका मन कैसे जांचकर जान सकते हो? नहीं, हे मेरे भाइयों, हमारे परमेश्वर को रिस न दिलाओ।"
    },
    {
      "verse": 15,
      "text": "क्योंकि यदि वह इन पांच दिनों के भीतर हमारी सहायता न करे, तो उस को हमारी रक्षा करने का अधिकार है, कि वह दिन भर हमारी रक्षा करे, या हमारे शत्रुओं के साम्हने हम को नाश करे।"
    },
    {
      "verse": 16,
      "text": "हमारे परमेश्वर की युक्‍ति को न बान्ध; क्योंकि परमेश्वर मनुष्य के तुल्य नहीं है, इसलिये कि उसे धमकी दी जाए; और न वह मनुष्य के पुत्रा के समान है, कि उस से बैर रखा जाए।"
    },
    {
      "verse": 17,
      "text": "इसलिये हम उस से उद्धार पाने की बाट जोहते रहें, और उस से प्रार्थना करें, कि वह हमारी सहायता करे; और यदि उस को प्रसन्‍न करे, तो हमारी सुन ले।"
    },
    {
      "verse": 18,
      "text": "क्योंकि हमारे बुढ़ापे में ऐसा कोई न हुआ, कि इन दिनों में न तो किसी गोत्रा का, न कोई गोत्रा, न कोई पुरूष, न हमारे बीच, न कोई नगर, जो पहिले के समान देवताओं की पूजा करता था।"
    },
    {
      "verse": 19,
      "text": "क्योंकि जिस कारण हमारे बापदादों को तलवार, और लूट दी गई थी, उसी ने हमारे शत्रुओं के साम्हने बड़ी मार खाई।"
    },
    {
      "verse": 20,
      "text": "परन्तु हम किसी और देवता को नहीं जानते, इसलिये हम भरोसा रखते हैं, कि वह न तो हम को तुच्छ जानेगा, और न हमारे जाति में से किसी को तुच्छ जानेगा।"
    },
    {
      "verse": 21,
      "text": "क्योंकि यदि हम ऐसे ले लिए जाएं, तो सारे यहूदिया उजड़ जाएंगे, और हमारा पवित्रास्थान नाश हो जाएगा; और वह हमारे मुंह से अशुद्ध ठहरने की आज्ञा देगा।"
    },
    {
      "verse": 22,
      "text": "और हमारे भाइयों का घात, और देश के बंधुओं का नाश, और हमारे निज भाग का उजड़ जाना, वह अन्यजातियों के बीच जहां हम दास होंगे हमारे सिर लौटा देगा; और हम अपने सब रहनेवालों के लिये ठोकर और नामधराई का कारण ठहरेंगे।"
    },
    {
      "verse": 23,
      "text": "क्योंकि हमारा दास अनुग्रह से प्रसन्न नहीं होता, परन्तु प्रभु हमारा परमेश्वर इसे बुराई की ओर खींच लेता है।"
    },
    {
      "verse": 24,
      "text": "इसलिये अब हे भाइयों, हम अपने भाइयों के लिये आदर्श दिखाएँ, क्योंकि उनका मन हम पर, और पवित्रास्थान, और भवन, और वेदी पर भरोसा रखता है, इसलिये कि उन का मन हम पर लगा रहता है।"
    },
    {
      "verse": 25,
      "text": "और हम अपने परमेश्वर यहोवा का धन्यवाद करें, जो हमारे बापदादों की नाई हमें जांचता है।"
    },
    {
      "verse": 26,
      "text": "याद करो, कि उस ने इब्राहीम से क्या किया, और उस ने इसहाक की परीक्षा कैसे की, और जब वह अपनी माता के भाई लाबान की भेड़ों को मानता था, तब अराम के ऊर नगर में याकूब के साथ क्या हुआ।"
    },
    {
      "verse": 27,
      "text": "क्योंकि उस ने हमें आग की नाई नहीं परखा, न उनके मन की जाँच की; न उस ने हम से बदला लिया; परन्तु प्रभु उन्हें जो उसके निकट आकर उन्हें चिताते हैं, चिताता है।"
    },
    {
      "verse": 28,
      "text": "तब दाऊद ने उस से कहा, जो कुछ तू ने भला कहा है, वह सब तू ने अच्छा मन कहा है, और कोई नहीं जो तेरे वचन कहे।"
    },
    {
      "verse": 29,
      "text": "क्योंकि यह वह पहिला दिन नहीं, जिस में तेरी बुद्धि प्रगट हुई, परन्तु तेरे दिनों से लेकर अब तक लोग तेरी समझ जानते आए हैं, क्योंकि तेरे मन का स्वभाव उत्तम है।"
    },
    {
      "verse": 30,
      "text": "परन्तु वे बहुत ही प्यासे थे, और जैसा हम ने कहा था, वैसा ही उन से करने को हमें मजबूर किया, कि हम उन पर ऐसी शपथ खाएँ, जिसे हम न तोड़ें।"
    },
    {
      "verse": 31,
      "text": "इसलिये अब तू हमारे लिये प्रार्थना कर, क्योंकि तू भक्त स्त्री है, और प्रभु हम को हमारे कुण्डों में भरने के लिये मेंह देगा, और हम फिर थक न जाएंगे।"
    },
    {
      "verse": 32,
      "text": "तब जूडिथ ने उन से कहा, मेरी सुनो, और मैं ऐसा काम करूंगा जो पीढ़ी से पीढ़ी तक हमारी जाति के लोगों के पास चलेगा।"
    },
    {
      "verse": 33,
      "text": "तुम आज ही रात फाटक में खड़े रहोगे, और मैं अपनी बाट जोहता रहूंगा; और जिन दिनों में तुम ने उस नगर को हमारे शत्रुओं के हाथ से छुड़ाने का वचन दिया है, उसी के भीतर प्रभु मेरे हाथ से इस्राएलियों की सुधि लेगा।"
    },
    {
      "verse": 34,
      "text": "परन्तु तुम मेरे काम के विषय में न कहना; क्योंकि जब तक मैं उन का अन्त न करूं, तब तक मैं तुम को नहीं बताता।"
    },
    {
      "verse": 35,
      "text": "तब अरज़ीया और हाकिमों ने उस से कहा, कुशल से जा, और प्रभु परमेश्वर तेरे साम्हने है, कि हम अपने शत्रुओं से पलटा लें।"
    },
    {
      "verse": 36,
      "text": "तब वे डेरे से लौटकर अपने अपने डेरे को चले गए।"
    }
  ]
}