{
  "book": "john",
  "chapter": 7,
  "verses": [
    {
      "verse": 1,
      "text": "इन बातों के बाद यीशु गलील में चला गया, क्योंकि यहूदियों ने उसे मार डालना चाहा था।"
    },
    {
      "verse": 2,
      "text": "अब यहूदियों का झोपड़ियों का पर्ब्ब निकट था ।"
    },
    {
      "verse": 3,
      "text": "तब उसके भाइयों ने उस से कहा, यहां से कूच करके यहूदिया में चला जा, कि तेरे चेले भी उन कामों को देखें जो तू करता है।"
    },
    {
      "verse": 4,
      "text": "क्योंकि गुप्त में कोई काम नहीं करता, और वह आप ही प्रगट करना चाहता है: यदि तू ऐसा करे, तो अपने आप को जगत पर प्रगट कर।"
    },
    {
      "verse": 5,
      "text": "क्योंकि उसके भाई उस पर विश्वास नहीं करते थे।"
    },
    {
      "verse": 6,
      "text": "यीशु ने उन से कहा, मेरा समय अभी नहीं आया; परन्तु तुम्हारा समय सदैव तैयार है।"
    },
    {
      "verse": 7,
      "text": "संसार तुम से बैर नहीं करता, परन्तु वह मुझ से बैर रखता है, क्योंकि मैं उस की गवाही देता हूं, कि उसके काम बुरे हैं।"
    },
    {
      "verse": 8,
      "text": "इस पर्ब्ब में जाओ, मैं अभी इस पर्ब्ब में नहीं जाता; क्योंकि मेरा समय अब तक पूरा नहीं हुआ।"
    },
    {
      "verse": 9,
      "text": "जब उस ने उन से ये बातें कहीं, तो वह गलील में रह गया।"
    },
    {
      "verse": 10,
      "text": "परन्तु जब उसके भाई वहां से चले गए, तो वह चुपके से नहीं, परन्तु मानों गुप्त होकर पर्ब्ब में गया।"
    },
    {
      "verse": 11,
      "text": "तब यहूदी पर्ब्ब में उसे ढूंढ़ने लगे, और कहने लगे, वह कहां है?"
    },
    {
      "verse": 12,
      "text": "और लोगों में उसके विषय में बहुत कुड़कुड़ाने लगा, क्योंकि कितने कहते थे, कि वह भला मनुष्य है; और कितने कहते थे, नहीं, वह लोगों को धोखा देता है।"
    },
    {
      "verse": 13,
      "text": "तौभी यहूदियों के डर के मारे कोई उस से खुलकर बात नहीं करता था।"
    },
    {
      "verse": 14,
      "text": "पर्ब्ब के बीच में यीशु मन्दिर में जाकर उपदेश करने लगा।"
    },
    {
      "verse": 15,
      "text": "और यहूदियों ने अचम्भा करके कहा, कि यह खत किस प्रकार जानता है, जिस ने कभी नहीं जाना?"
    },
    {
      "verse": 16,
      "text": "यीशु ने उन्हें उत्तर दिया, कि मेरा उपदेश मेरा नहीं, परन्तु मेरे भेजनेवाले का है।"
    },
    {
      "verse": 17,
      "text": "यदि कोई उस की इच्छा पर चले, तो वह इस उपदेश के विषय में जान लेगा, कि वह परमेश्वर की ओर से है, या मैं अपनी ओर से कहता हूं।"
    },
    {
      "verse": 18,
      "text": "जो कोई अपने आप से कुछ कहता है, वह अपनी ही महिमा चाहता है; परन्तु जो अपने भेजनेवाले की बड़ाई चाहता है, वही सच्चा है; और उस में कुटिलता नहीं।"
    },
    {
      "verse": 19,
      "text": "क्या मूसा ने तुम्हें व्यवस्था नहीं दी, परन्तु तुम में से कोई भी व्यवस्था को नहीं मानता? तुम मुझे मारने के लिये क्यों जाते हो?"
    },
    {
      "verse": 20,
      "text": "लोगों ने उत्तर दिया, कि तेरे पास दुष्टात्मा है; कौन तुझे मार डालना चाहता है?"
    },
    {
      "verse": 21,
      "text": "यीशु ने उन को उत्तर दिया, कि मैं ने एक काम किया है, और तुम सब आश्चर्य करते हो।"
    },
    {
      "verse": 22,
      "text": "इसलिये मूसा ने तुम लोगों को खतना कराया (यह तो मूसा की ओर से नहीं, परन्तु बापदादों की है) और तुम सब्त के दिन मनुष्य का खतना करते हो।"
    },
    {
      "verse": 23,
      "text": "यदि सब्त के दिन कोई मनुष्य खतना ले, जिस से मूसा की व्यवस्था तोड़ी न जाए, तो क्या तुम मुझ पर क्रोध करते हो, क्योंकि मैं ने सब्त के दिन मनुष्य को पूरी रीति से बना दिया है?"
    },
    {
      "verse": 24,
      "text": "प्रगट में न्याय न करना, परन्तु ठीक ठीक न्याय चुकाना।"
    },
    {
      "verse": 25,
      "text": "तब यरूशलेम में से कितनों ने कहा, क्या यह वही नहीं, जिस को वे मार डालना चाहते हैं?"
    },
    {
      "verse": 26,
      "text": "परन्तु देखो, वह निडर होकर बातें करता है, और वे उस से कुछ नहीं कहते: क्या सरदारों ने सचमुच यह जान लिया है कि यही मसीह है?"
    },
    {
      "verse": 27,
      "text": "परन्तु हम जानते हैं, कि यह कहां का है, परन्तु मसीह जब आएगा, तो कोई नहीं जानता, कि वह कहां का है।"
    },
    {
      "verse": 28,
      "text": "तब यीशु ने मन्दिर में उपदेश देते हुए पुकारकर कहा, तुम मुझे जानते हो, और यह भी जानते हो, कि मैं कहां का हूं; और मैं अपने आप से नहीं आया, परन्तु मेरा भेजा हुआ सच्चा है, जिसे तुम नहीं जानते।"
    },
    {
      "verse": 29,
      "text": "परन्तु मैं उसे जानता हूं, क्योंकि मैं उस की ओर से हूं, और उसी ने मुझे भेजा है।"
    },
    {
      "verse": 30,
      "text": "तब उन्हों ने उसे पकड़ना चाहा, परन्तु किसी ने उस पर हाथ न डाला, क्योंकि उसका समय अब तक न आया था।"
    },
    {
      "verse": 31,
      "text": "और भीड़ में से बहुतेरों ने उस पर विश्वास किया, और कहने लगे, कि मसीह कब आएगा, तो क्या इस से अधिक चमत्कार करेगा?"
    },
    {
      "verse": 32,
      "text": "तब फरीसियों ने सुना, कि लोग उसके विषय में ऐसी बातें बकते हैं; और फरीसियों और महायाजकों ने उसे पकड़ने के लिये सिपाही भेजे।"
    },
    {
      "verse": 33,
      "text": "यीशु ने उन से कहा, थोड़े दिन के बीतने पर मैं अपने भेजनेवाले के पास जाता हूं।"
    },
    {
      "verse": 34,
      "text": "तुम मुझे ढूंढ़ोगे, परन्तु न पाओगे; और जहां मैं हूं वहां तुम नहीं आ सकते।"
    },
    {
      "verse": 35,
      "text": "यहूदियों ने आपस में कहा, वह कहां जाएगा, कि हम उसे न पाएंगे? क्या वह अन्यजातियों में तितर बितर होकर अन्यजातियों को उपदेश देगा?"
    },
    {
      "verse": 36,
      "text": "यह क्या बात है जो उस ने कही, कि तुम मुझे ढूंढ़ोगे, और न पाओगे; और जहां मैं हूं, वहां तुम नहीं आ सकते?"
    },
    {
      "verse": 37,
      "text": "और पर्ब्ब के उस बड़े दिन को यीशु खड़ा हुआ और पुकारकर कहने लगा, यदि कोई प्यासा हो तो मेरे पास आकर पीए।"
    },
    {
      "verse": 38,
      "text": "जो मुझ पर विश्वास करता है, जैसा पवित्रा शास्त्रा में कहा गया है, उसके पेट से जीवन के जल की धारा बहती है।"
    },
    {
      "verse": 39,
      "text": "उस ने यह बात उस आत्मा के विषय में कही, जो उस पर विश्वास करनेवालों को चाहिए था, क्योंकि पवित्रा आत्मा अब तक नहीं उतरा था, क्योंकि यीशु अब तक अपनी महिमा नहीं कर रहा था।"
    },
    {
      "verse": 40,
      "text": "तब लोगों में से बहुतेरों ने यह सुनकर कहा, सचमुच यही भविष्यद्वक्ता है।"
    },
    {
      "verse": 41,
      "text": "औरों ने कहा, यह मसीह है: परन्तु कितने कहने लगे, क्या मसीह गलील से आएगा?"
    },
    {
      "verse": 42,
      "text": "क्या पवित्रा शास्त्रा ने नहीं कहा, कि मसीह दाऊद के वंश से, और बैतलहम नगर में जहां दाऊद रहता था, आएगा?"
    },
    {
      "verse": 43,
      "text": "सो उसके कारण लोगों में फूट पड़ी।"
    },
    {
      "verse": 44,
      "text": "और उन में से कितने उसे पकड़ना चाहते थे, परन्तु किसी ने उस पर हाथ नहीं डाला।"
    },
    {
      "verse": 45,
      "text": "तब प्यादों ने महायाजकों और फरीसियों के पास आकर उन से पूछा, तुम उसे क्यों नहीं लाए?"
    },
    {
      "verse": 46,
      "text": "सिपाहियों ने उत्तर दिया, कि किसी मनुष्य ने कभी ऐसी बातें न कीं।"
    },
    {
      "verse": 47,
      "text": "फरीसियों ने उन को उत्तर दिया, क्या तुम भी धोखा देते हो?"
    },
    {
      "verse": 48,
      "text": "क्या सरदारों या फरीसियों में से किसी ने उस पर विश्वास किया?"
    },
    {
      "verse": 49,
      "text": "परन्तु ये लोग जो व्यवस्था को नहीं जानते, स्रापित हैं।"
    },
    {
      "verse": 50,
      "text": "नीकुदेमुस ने उन से कहा; जो रात को यीशु के पास आया था, वह उन में से एक था।"
    },
    {
      "verse": 51,
      "text": "क्या हमारी व्यवस्था किसी मनुष्य को उसके सुनने से पहिले दोषी बनाती है, और जानता है कि वह क्या करता है?"
    },
    {
      "verse": 52,
      "text": "उन्हों ने उस को उत्तर दिया, क्या तू भी गलील का है? खोजकर देख, क्योंकि गलील से कोई भविष्यद्वक्ता नहीं उठता।"
    },
    {
      "verse": 53,
      "text": "तब हर एक अपने घर चला गया।"
    }
  ]
}