{
  "book": "ps",
  "chapter": 54,
  "verses": [
    {
      "verse": 1,
      "text": "हे परमेश्वर, अपने नाम के द्वारा मेरा उद्धार कर, और अपनी शक्ति से मेरा न्याय कर।"
    },
    {
      "verse": 2,
      "text": "हे परमेश्वर, मेरी प्रार्थना सुन ले; मेरे मुंह के वचनों की ओर कान लगा!"
    },
    {
      "verse": 3,
      "text": "क्योंकि परदेशी मेरे विरूद्ध उठे हैं, और अन्धेर करनेवाले मेरे प्राण के खोजी हैं; उन्हों ने परमेश्वर को अपने साम्हने नहीं रखा।।"
    },
    {
      "verse": 4,
      "text": "देखो, परमेश्वर मेरा सहायक है; प्रभु मेरे प्राण के रक्षकों के संग है।"
    },
    {
      "verse": 5,
      "text": "वह मेरे द्रोहियों को बुरा फल देगा; वे तेरे सच्चाई के कारण नाश होंगे।"
    },
    {
      "verse": 6,
      "text": "मैं तुझ को मुफ्त में बलिदान करूंगा; हे यहोवा, मैं तेरे नाम की स्तुति करूंगा, क्योंकि वह भला है।"
    },
    {
      "verse": 7,
      "text": "क्योंकि उस ने मुझे सब दु:खों से छुड़ाया है, और मेरी लालसा मेरे शत्रुओं पर प्रगट हुई है।"
    }
  ]
}