{
  "book": "ezra",
  "chapter": 2,
  "verses": [
    {
      "verse": 1,
      "text": "जिनको बाबेल का राजा नबूकदनेस्सर बाबेल को ले गया था, उन में से प्रान्त के जो लोग बन्धुआई से चले गए थे, वे ये हैं, और यरूशलेम और यहूदा में अपने अपने अपने नगर को लौट गए थे।"
    },
    {
      "verse": 2,
      "text": "और जरूब्बाबेल, येशू, सरायाह, सरायाह, मोर्दकै, बिलशान, मित्ती, बिगवै, रहूम और इस्राएल के लोगों की गिनती।"
    },
    {
      "verse": 3,
      "text": "परोश की सन्तान दो हजार एक सौ सत्तर।"
    },
    {
      "verse": 4,
      "text": "शपत्याह की सन्तान तीन सौ तिहत्तर,"
    },
    {
      "verse": 5,
      "text": "आरह की सन्तान सात सौ पछहत्तर,"
    },
    {
      "verse": 6,
      "text": "पहत्मोआब की सन्तान येशू और योआब की सन्तान में से दो हजार आठ सौ बारह।"
    },
    {
      "verse": 7,
      "text": "एलाम की सन्तान बारह सौ साढ़े चार।"
    },
    {
      "verse": 8,
      "text": "जत्तू की सन्तान नौ सौ पैंतालीस।"
    },
    {
      "verse": 9,
      "text": "जक्कै की सन्तान सात सौ साठ।"
    },
    {
      "verse": 10,
      "text": "बानी की सन्तान छ: सौ बयालीस"
    },
    {
      "verse": 11,
      "text": "बेबै की सन्तान छेसौ तेईस,"
    },
    {
      "verse": 12,
      "text": "अजगाद की सन्तान बारह सौ बाईस,"
    },
    {
      "verse": 13,
      "text": "अदोनीकाम की सन्तान छ: सौ साठ।"
    },
    {
      "verse": 14,
      "text": "बिग्वै की सन्तान दो हजार छप्पन,"
    },
    {
      "verse": 15,
      "text": "आदीन की सन्तान चार सौ चार।"
    },
    {
      "verse": 16,
      "text": "हिजकिरयाह के वंश में से अट्ठानवे।"
    },
    {
      "verse": 17,
      "text": "बेसै की सन्तान तीन सौ तेईस,"
    },
    {
      "verse": 18,
      "text": "योरा की सन्तान एक सौ बारह।"
    },
    {
      "verse": 19,
      "text": "हाशूम की सन्तान दो सौ तेईस,"
    },
    {
      "verse": 20,
      "text": "गिब्बार के लोग पंचानवे।"
    },
    {
      "verse": 21,
      "text": "बेतलेहेम के लोग एक सौ तेईस,"
    },
    {
      "verse": 22,
      "text": "नकोश के मनुष्य छ:,"
    },
    {
      "verse": 23,
      "text": "अनातोत के मनुष्य एक सौ अट्ठाईस।"
    },
    {
      "verse": 24,
      "text": "हारीम की सन्तान चालीस।"
    },
    {
      "verse": 25,
      "text": "किर्यत्यारीम, कपीरा, और बेरोत की सन्तान सात सौ तैतालीस,"
    },
    {
      "verse": 26,
      "text": "रामा और गाब की सन्तान छेसौ बीस।"
    },
    {
      "verse": 27,
      "text": "मिस्मा के मनुष्य एक सौ बाईस।"
    },
    {
      "verse": 28,
      "text": "बेतेल और ऐ के मनुष्य दो सौ तेईस,"
    },
    {
      "verse": 29,
      "text": "नबो के लोग बावन,"
    },
    {
      "verse": 30,
      "text": "मब की सन्तान एक सौ छप्पन।"
    },
    {
      "verse": 31,
      "text": "दूसरे एलाम की सन्तान बारह सौ साढ़े चार।"
    },
    {
      "verse": 32,
      "text": "हारीम की सन्तान तीन सौ बीस।"
    },
    {
      "verse": 33,
      "text": "लोद, हदद, ओनो, सात सौ पच्चीस।"
    },
    {
      "verse": 34,
      "text": "यरीहो के लोग तीन सौ पैंतालीस।"
    },
    {
      "verse": 35,
      "text": "सना के लोग तीन हजार छ: सौ तीस।"
    },
    {
      "verse": 36,
      "text": "और याजक अर्थात् येशू के घराने में से यदायाह की सन्तान नौ सौ तिहत्तर।"
    },
    {
      "verse": 37,
      "text": "इम्मेर की सन्तान एक हजार पचास।"
    },
    {
      "verse": 38,
      "text": "पशहूर की सन्तान बारह सौ पैंतालीस।"
    },
    {
      "verse": 39,
      "text": "हारीम की सन्तान एक हजार सतरह।"
    },
    {
      "verse": 40,
      "text": "फिर लेवीय ये थे; अर्थात् होदिरयाह की सन्तान में से येशू की सन्तान सत्तर।"
    },
    {
      "verse": 41,
      "text": "फिर गवैये ये थे अर्थात् आसाप की सन्तान एक सौ अट्ठाईस।"
    },
    {
      "verse": 42,
      "text": "फिर द्वारपालों की सन्तान, शल्लूम की सन्तान, तल्मोन की सन्तान, तल्मोन की सन्तान, हतीता की सन्तान, और शोबै की सन्तान, जो सब मिलकर एक सौ नौ।"
    },
    {
      "verse": 43,
      "text": "फिर नतीन की सन्तान, सीहा की सन्तान, हसूपा की सन्तान, तब्बाओत की सन्तान,"
    },
    {
      "verse": 44,
      "text": "केरोस की सन्तान, सीसे की सन्तान, पादोन की सन्तान,"
    },
    {
      "verse": 45,
      "text": "लबान की सन्तान, हगाबा की सन्तान, तलूब की सन्तान,"
    },
    {
      "verse": 46,
      "text": "हगाब की सन्तान, शमै की सन्तान, रिम्मोन की सन्तान,"
    },
    {
      "verse": 47,
      "text": "गिडल की सन्तान, गहर की सन्तान, रायाह की सन्तान,"
    },
    {
      "verse": 48,
      "text": "रसीन की सन्तान, नकोदा की सन्तान, गज्जाम की सन्तान,"
    },
    {
      "verse": 49,
      "text": "उज्जा की सन्तान, पासेह की सन्तान, बेसै की सन्तान,"
    },
    {
      "verse": 50,
      "text": "अस्ना की सन्तान, मिशम की सन्तान, निमम की सन्तान,"
    },
    {
      "verse": 51,
      "text": "बकबूक की सन्तान, हकूपा की सन्तान, हर्हूर की सन्तान,"
    },
    {
      "verse": 52,
      "text": "बसद की सन्तान, महीदा की सन्तान, हर्शा की सन्तान,"
    },
    {
      "verse": 53,
      "text": "बारोस की सन्तान, सीसरा की सन्तान, हा्मा की सन्तान,"
    },
    {
      "verse": 54,
      "text": "नन्याह की सन्तान, और हतीपा की सन्तान।"
    },
    {
      "verse": 55,
      "text": "फिर सुलैमान के दासों की सन्तान, सोतै की सन्तान, सोपेर की सन्तान, पेरू की सन्तान,"
    },
    {
      "verse": 56,
      "text": "याला की सन्तान, गहरेन की सन्तान, गि :ल की सन्तान,"
    },
    {
      "verse": 57,
      "text": "यिसहार की सन्तान, हत्तील की सन्तान, पोतैम की सन्तान, और आमी की सन्तान।"
    },
    {
      "verse": 58,
      "text": "नतीन और सुलैमान के दासों की सन्तान तीन सौ नब्बे थे ।"
    },
    {
      "verse": 59,
      "text": "और तेलहहह, तेलहर्शा, करूब, और इम्मेर से निकले ये थे; परन्तु वे अपने पिता के घराने और अपने वंश को न बता सके कि वे इस्राएल के हैं वा नहीं।"
    },
    {
      "verse": 60,
      "text": "अर्थात् नकोदा की सन्तान, राजायाह की सन्तान, नकोदा की सन्तान, छ: सौ बावन।"
    },
    {
      "verse": 61,
      "text": "और याजकों की सन्तान में से हबायाह की सन्तान, कोस की सन्तान, बर्जिल्लै की सन्तान, जिस ने गिलादी बर्जिल्लै की बेटियों में से एक को ब्याह लिया, और उनका नाम रख लिया।"
    },
    {
      "verse": 62,
      "text": "इन्हों ने अपनी वंशावली के अनुसार अपनी वंशावली का लेख ढूंढ़ने पर भी न पाया; इस कारण वे अशुठ्ठ होने के कारण याजकपद से निकाले गए।"
    },
    {
      "verse": 63,
      "text": "और अधिपति ने उन से कहा, जब तक ऊरीम और तुम्मीम धारण करनेवाला कोई याजक न हो, तब तक वे परमपवित्रा वस्तुओं में से खाने न पाएं।"
    },
    {
      "verse": 64,
      "text": "सारी मण्डली मिलकर बयालीस हजार तीन सौ साठ थी।"
    },
    {
      "verse": 65,
      "text": "और उनके अलावा सात हजार तीन सौ तीस दास- दासियां भी थीं; और उन में से दो सौ गानेवालियां और गानेवालियां थीं।"
    },
    {
      "verse": 66,
      "text": "उनके घोड़े सात सौ तीस, खच्चर दो सौ पैंतालीस,"
    },
    {
      "verse": 67,
      "text": "ऊंट चार सौ पैंतीस, गदहे छे हजार सात सौ बीस।"
    },
    {
      "verse": 68,
      "text": "और पितरों के घरानों के मुख्य मुख्य मुख्य पुरूषों ने जब यहोवा के भवन में, जो यरूशलेम में है, आकर परमेश्वर के भवन को उसके स्थान पर खड़ा करने के लिये अपनी इच्छा से भेंट चढ़ाई।"
    },
    {
      "verse": 69,
      "text": "और उन्हों ने अपनी अपनी पूंजी के अनुसार काम के सत्तर हजार दर्कमोन सोना, पांच हजार माने चान्दी, और एक सौ याजक थे।"
    },
    {
      "verse": 70,
      "text": "तब याजक और लेवीय और प्रजा के कुछ लोग, गवैये, द्वारपाल और नतीन लोग अपने नगर में और सब इस्राएली अपने अपने नगर में बस गए।"
    }
  ]
}