{
  "book": "jdt",
  "chapter": 4,
  "verses": [
    {
      "verse": 1,
      "text": "और जो इस्राएली यहूदिया में रहते थे, उन्हों ने सुना, कि अश्शूर के राजा नकोदोन के सेनापति ने अन्यजातियों से क्या किया था, और उसके बाद उस ने उनके सारे मन्दिरों को लूट लिया, और उन्हें निकम्मा कर दिया।"
    },
    {
      "verse": 2,
      "text": "इस कारण वे उस से अत्यन्त डर गए, और यरूशलेम और अपने परमेश्वर के मन्दिर के लिये घबरा गए।"
    },
    {
      "verse": 3,
      "text": "क्योंकि वे बन्धुआई से लौटे हुए थे, और यहूदियों के सब लोग हाल ही में इकट्ठे हुए थे; और पात्रा और वेदी और भवन पवित्रा किए गए थे।"
    },
    {
      "verse": 4,
      "text": "इस कारण उन्हों ने शोमरोन के सारे देश में, और गांवों, और बेथोरों, और बेल्मोन, यरीहो, यालाबा, और एराम नाम तराई को भेज दिया।"
    },
    {
      "verse": 5,
      "text": "और उस ने पहिले से ऊंचे पहाड़ों की सब चोटियों पर अधिकारी होकर उन के गांवों को दृढ़ किया, और लड़ाई के लिये भोजनवस्तु रखी; क्योंकि उनके खेत कटनी के समय थोड़े ही समय के थे।"
    },
    {
      "verse": 6,
      "text": "फिर योशिरयाह महायाजक जो यरूशलेम के उन दिनों में था, उन लोगों को जो बेथोथिया में रहते थे, और बेथेन में, जो खुले देश के पास दोनाम नगर के पास रहते थे, यह लिख चुका था।"
    },
    {
      "verse": 7,
      "text": "और पहाड़ी देश के उपदेश को मानते थे, क्योंकि उन के द्वारा यहूदिया में एक द्वार था, और जो लोग आते थे, उन्हें रोक देना आसान था, क्योंकि वह मार्ग सीधे था, क्योंकि उस में दो मनुष्य थे।"
    },
    {
      "verse": 8,
      "text": "और इस्राएलियों ने योममम महायाजक की आज्ञा के अनुसार, यरूशलेम में रहनेवाले सब इस्राएली लोगों के पुरनियों के संग किया।"
    },
    {
      "verse": 9,
      "text": "तब इस्राएल के सब पुरूष बड़े छली होकर परमेश्वर की दोहाई देते थे, और बड़ी कठोरता से अपने मन को नम्र करते थे।"
    },
    {
      "verse": 10,
      "text": "और उन्हों ने अपनी स्त्रियों, पुत्रों, भेड़- बकरी, गाय- बैल, और सब परदेशी, और मजदूरों को मोल लिया, और अपनी अपनी कमर में टाट बान्ध लिया।"
    },
    {
      "verse": 11,
      "text": "इस प्रकार सब पुरूष और स्त्री और बालक और यरूशलेम के निवासी मन्दिर के साम्हने गिरे, और अपने अपने सिर पर राख डालकर प्रभु के साम्हने टाट फैलाए; और उन्हों ने वेदी की चारों ओर टाट बान्धा।"
    },
    {
      "verse": 12,
      "text": "और इस्राएल के परमेश्वर की यह वाणी है, कि वह अपने लड़केबालों को लूट के लिये, और अपनी स्त्रियों को लूट के लिये, और अपने निज भाग के नगरों को नाश करने के लिये नाश करने, और पवित्रास्थान को अपवित्रा करने, और अन्यजातियों पर आनन्द करने के लिये न देगा।"
    },
    {
      "verse": 13,
      "text": "तब परमेश्वर ने उनकी प्रार्थना सुनी, और उन के क्लेशों पर दृष्टि की; क्योंकि वे सब यहूदिया और यरूशलेम में सर्वशक्तिमान प्रभु के पवित्रास्थान के साम्हने बहुत दिन तक उपवास करते रहे।"
    },
    {
      "verse": 14,
      "text": "और योशिरयाह महायाजक और जितने याजक प्रभु के सम्मुख खड़े थे, और जो लोग प्रभु की सेवा टहल कर रहे थे, उन सभों के कमर में टाट बान्धे हुए थे, और प्रति दिन के होमबलि और प्रजा के लिये भेंट चढ़ाया करते थे।"
    },
    {
      "verse": 15,
      "text": "और उन की सारी शक्ति के साथ प्रभु की दोहाई दी, कि वह इस्राएल के सारे घराने पर अनुग्रह करे।"
    }
  ]
}