{
  "book": "sus",
  "chapter": 1,
  "verses": [
    {
      "verse": 1,
      "text": "बाबुल में एक पुरूष रहता था, जो योकाम कहलाता था।"
    },
    {
      "verse": 2,
      "text": "और उस ने एक स्त्री को ब्याह लिया, जिस का नाम सूशा था, जो कुएं की बेटी थी, और जो बहुत सुन्दर थी, और प्रभु का भय मानती थी।"
    },
    {
      "verse": 3,
      "text": "उसके माता- पिता भी धर्मी थे, और अपनी बेटी को मूसा की व्यवस्था के अनुसार सिखाया करते थे।"
    },
    {
      "verse": 4,
      "text": "योयाम एक धनी मनुष्य था, और उसके घर में एक सुन्दर बारी थी; और वह यहूदियों का साम्हना करने को तैयार था, क्योंकि वह सब से अधिक प्रतिष्ठित था।"
    },
    {
      "verse": 5,
      "text": "उसी वर्ष लोगों में से दो तो न्यायी ठहराए गए, जैसे कि प्रभु ने कहा था, कि बाबुल से दुष्टता प्राचीन न्यायियों में से आई, जो लोगों पर प्रभुता करना चाहते थे।"
    },
    {
      "verse": 6,
      "text": "वे योमम के घर में बहुत रहते थे, और जो कुछ व्यवस्था में था, वह सब उन के पास पहुंचा।"
    },
    {
      "verse": 7,
      "text": "अब जब लोग दोपहर को चले गए, सूज़न अपने पति की बारी में चलने चली गयी ।"
    },
    {
      "verse": 8,
      "text": "तब उन दोनों प्राचीनों ने प्रति दिन उसे जाते देखकर चलते हुए देखा, यहां तक कि उन की लालसा उसके साम्हने बुरी हो गई।"
    },
    {
      "verse": 9,
      "text": "और उन्हों ने अपने मन को उलट पुलट कर डाला, और अपनी आंखों से देखा, कि स्वर्ग की ओर न देखें, और न न्याय की चर्चा करें।"
    },
    {
      "verse": 10,
      "text": "परन्तु वे दोनों उसके प्रेम से घायल हुए, तौभी एक दूसरे को उसका शोक न जताए।"
    },
    {
      "verse": 11,
      "text": "क्योंकि वे अपनी इच्छा का प्रचार करने से लज्जित हुए, कि उसके साथ क्या करना चाहते हैं।"
    },
    {
      "verse": 12,
      "text": "फिर भी वे उसे देखने के लिए दिन - ब - दिन यत्न करते रहे ।"
    },
    {
      "verse": 13,
      "text": "एक ने दूसरे से कहा, आओ, हम घर चलें; क्योंकि यह भोज का समय है।"
    },
    {
      "verse": 14,
      "text": "सो जब वे बाहर निकल गए, तो एक दूसरे से अलग हो गए, और एक ही जगह में लौट गए; और जब वे आपस में विचार कर रहे थे, तो एक दूसरे से पूछने लगे; तब उन्हों ने एक ही बार फिर अपनी इच्छा मान ली।"
    },
    {
      "verse": 15,
      "text": "और ऐसा हुआ, कि जैसा उन्हों ने ठीक समय पर देखा, वैसा ही उस ने भी किया, अर्थात् दो लौंडियों के संग वैसा ही हुआ, और वह बारी में अपने आप को धोना चाहती थी; क्योंकि वह गर्म थी।"
    },
    {
      "verse": 16,
      "text": "और उन दोनों प्राचीनों को छोड़ कोई देह न थी, जिन्हों ने आप को छिपा रखा था, और उस की ताक में रहा।"
    },
    {
      "verse": 17,
      "text": "तब उस ने अपनी दासियों से कहा, मेरे पास तेल और कुप्पी ले आओ, और बारी के द्वार बन्द कर दो, कि मैं स्नान करूं।"
    },
    {
      "verse": 18,
      "text": "और जैसे उस ने उन्हें आज्ञा दी थी, वैसे ही वे बारी के द्वार बन्द करके बाहर गए, कि जो कुछ उस ने उन्हें आज्ञा दी थी, उसे ले आएं; परन्तु प्राचीनों को इसलिये न देखा, कि वे छिप गए हैं।"
    },
    {
      "verse": 19,
      "text": "जब कुमारियां निकल गई, तो उन दो प्राचीन उठकर उस के पास दौड़ गए,"
    },
    {
      "verse": 20,
      "text": "देख, बारी के द्वार बन्द हैं, कि कोई हमें देख नहीं सकता, और हम तुझ से प्रेम रखते हैं; इसलिये तू हमारी बात मान और हमारे साथ सो।"
    },
    {
      "verse": 21,
      "text": "यदि तू न माने, तो हम तेरे विरूद्ध साक्षी देंगे, कि तेरे संग एक जवान पुरूष था; इस कारण तू अपनी लौंडियों को तुझ से विदा किया।"
    },
    {
      "verse": 22,
      "text": "तब सूज़ाना ने आह मारकर कहा, मैं चारों ओर से दबा हुआ हूं; क्योंकि यदि मैं ऐसा करता हूं, तो मेरी मृत्यु है; और यदि मैं ऐसा न करूं, तो तुम्हारे हाथ से बच नहीं सकता।"
    },
    {
      "verse": 23,
      "text": "प्रभु के साम्हने पाप करने से मैं तेरे हाथ में पड़ूं, और ऐसा न कर।"
    },
    {
      "verse": 24,
      "text": "तब सूज़ाना ऊंचे शब्द से चिल्ला उठी, और उन दोनों प्राचीनों ने उसके विरोध में चिल्लाकर कहा।"
    },
    {
      "verse": 25,
      "text": "तब उस ने दौड़कर बाटिका का द्वार खोल दिया।"
    },
    {
      "verse": 26,
      "text": "जब घर के कर्मचारियों ने बारी में दोहाई दी, तब वे उस सोते के द्वार पर दौड़ गए, कि जो कुछ उस से किया गया था, वह देखने को आए।"
    },
    {
      "verse": 27,
      "text": "परन्तु जब प्राचीनों ने यह बात कही, तब दास बहुत लज्जित हुए; क्योंकि ऐसा कभी न हुआ कि सूना की ऐसी एक ऐसी रिपोर्ट हुई।"
    },
    {
      "verse": 28,
      "text": "दूसरे दिन जब लोग अपने पति योशाम के पास इकट्ठे हुए, तब उन दोनों प्राचीन भी सूशा के विरूद्ध दुष्टता की कल्पना करने लगे, कि उसे मरवा डाले।"
    },
    {
      "verse": 29,
      "text": "और लोगों के सामने कहा, शिल्सिया की बेटी, योम की पत्नी, सूज़नना को भेजें ।"
    },
    {
      "verse": 30,
      "text": "सो वह अपने पिता और माता और लड़केबालों और अपने सब कुटुम्बियों के साथ आई।"
    },
    {
      "verse": 31,
      "text": "अब सूज़न एक बहुत ही नाज़ुक और खूबसूरत लड़की थी ।"
    },
    {
      "verse": 32,
      "text": "और उन दुष्ट पुरूषों ने यह आज्ञा दी, कि अपना मुंह दिखाने की आज्ञा दे, कि वह अपनी सुन्दरता से परिपूर्ण हो जाए।"
    },
    {
      "verse": 33,
      "text": "तब उसके मित्रा और जितने उसे देखते थे, सब रोने लगे।"
    },
    {
      "verse": 34,
      "text": "तब वे दोनों प्राचीन प्रजा के बीच में खड़े होकर अपने हाथ उसके सिर पर रखे।"
    },
    {
      "verse": 35,
      "text": "और वह रोने लगी, क्योंकि उसका मन प्रभु पर भरोसा रखता था।"
    },
    {
      "verse": 36,
      "text": "प्राचीनों ने कहा, जब हम दोनों बारी में चलते थे, तब यह स्त्री दो लौंडियों के साथ भीतर आई, और बारी के द्वार बन्द करके लौंडियों को विदा किया।"
    },
    {
      "verse": 37,
      "text": "तब एक जवान जो छिप गया था, उसके पास आया, और उसके साथ कुकर्म किया।"
    },
    {
      "verse": 38,
      "text": "तब हम जो बाटिका के एक कोने में खड़े थे, यह बुराई देखकर उन के पास दौड़ गए।"
    },
    {
      "verse": 39,
      "text": "और जब हम ने उन्हें देखा, तो वह पुरूष हम को पकड़ न सका; क्योंकि वह हम से बलवन्त था, और द्वार खोलकर बाहर चला गया।"
    },
    {
      "verse": 40,
      "text": "परन्तु उस स्त्री को लेकर हम ने पूछा, कि वह जवान कौन है, परन्तु वह हम से न कहती थी, कि हम इन बातों की गवाही देते हैं।"
    },
    {
      "verse": 41,
      "text": "तब मण्डली के लोगों के पुरनियों और न्यायियों की नाई उन की प्रतीति की, और उन्हों ने उसे मार डालने की आज्ञा दी।"
    },
    {
      "verse": 42,
      "text": "तब सूज़ाना ऊंचे शब्द से चिल्ला उठी, हे सनातन परमेश्वर, जो भेदों को जानता है, और उनके होने से पहिले सब कुछ जानता है।"
    },
    {
      "verse": 43,
      "text": "तू जानता है, कि उन्हों ने मेरे विरूद्ध झूठी साक्षी दी है, और मैं अवश्य मर जाऊंगा; परन्तु मैं ने ऐसी बातें कभी नहीं की।"
    },
    {
      "verse": 44,
      "text": "और प्रभु ने उसकी बात सुन ली।"
    },
    {
      "verse": 45,
      "text": "सो जब वह मार डालने के लिये लाई गई, तो प्रभु ने एक जवान जवान की पवित्रा आत्मा को जिस का नाम दानिरयेल था, खड़ा किया।"
    },
    {
      "verse": 46,
      "text": "वह ऊंचे शब्द से पुकार कर कहता था, कि मैं इस स्त्री के लोहू से निर्दोष हूं।"
    },
    {
      "verse": 47,
      "text": "तब सब लोग उसकी ओर फिरकर कहने लगे, तू ने ये वचन क्या कहा है?"
    },
    {
      "verse": 48,
      "text": "तब वह उनके बीच खड़ा होकर कहने लगा, हे इस्त्राएलियों, क्या तुम ऐसे मूर्ख हो, जो सत्य की खोज या ज्ञान के बिना इस्राएल की बेटी को दोषी ठहराते हो?"
    },
    {
      "verse": 49,
      "text": "न्याय के स्थान में लौट आओ, क्योंकि उन्हों ने उसके विरूद्ध झूठी साक्षी दी है।"
    },
    {
      "verse": 50,
      "text": "इस कारण सब लोग तुरन्त मुंह फेरकर उस से कहने लगे, आ, हम में बैठ जा, और यह हमें बता दे, कि परमेश्वर ने तुझे प्राचीन का आदर किया है।"
    },
    {
      "verse": 51,
      "text": "तब दानिरयेल ने उन से कहा, इन दोनों को एक दूसरे से दूर रखो, और मैं उन्हें जांचूंगा।"
    },
    {
      "verse": 52,
      "text": "जब वे एक दूसरे से अलग हो गए, तो उस ने उन में से एक को बुलाकर उस से कहा, हे कुकर्म करनेवालो, तेरे पाप अब प्रगट हुए हैं।"
    },
    {
      "verse": 53,
      "text": "क्योंकि तू ने झूठे न्याय का प्रचार किया है, और निर्दोषों को दोषी ठहराया है, और दोषी को स्वतंत्रा होने दिया है; तौभी प्रभु कहता है, निर्दोष और धर्मी दोनों को घात न करना।।"
    },
    {
      "verse": 54,
      "text": "सो अब यदि तू उसे देखे, तो मुझ से कह, कि तू ने किस पेड़ के तले, जो वृक्ष तुझे देखा है, वह आपस में मिल गया है? किस ने उत्तर दिया, एक राजक वृक्ष के तले।"
    },
    {
      "verse": 55,
      "text": "दानिरयेल ने कहा, बहुत अच्छा, तू ने अपने सिर के विरूद्ध झूठ बोला है, क्योंकि अब तक परमेश्वर के दूत को तुझे दो टुकड़े करने की आज्ञा मिल गई है।"
    },
    {
      "verse": 56,
      "text": "तब उस ने उसको अलग अलग करके दूसरे को लाने की आज्ञा दी, और उस से कहा, हे सिनाअन के वंश, तू ने तो यहूदा के न तो तुझे धोखा दिया, और न अपनी अभिलाषा को उलट दिया है।"
    },
    {
      "verse": 57,
      "text": "तुम ने इस्राएल की बेटियों से ऐसा बर्ताव किया, और वे तेरे साथ भययोग्य हैं; परन्तु यहूदा की बेटी तेरी बुराई न रहने पाएगी।"
    },
    {
      "verse": 58,
      "text": "सो अब मुझ से कह, तू ने किस वृक्ष के तले उन की संगति की? किस ने उत्तर दिया, एक गढ़वाले वृक्ष के तले।"
    },
    {
      "verse": 59,
      "text": "तब दानिरयेल ने उस से कहा, तू ने तो अपने सिर के विरूद्ध झूठ बोला है; क्योंकि परमेश्वर का दूत तलवार से तेरी हानि करने की आशा रखता है, कि वह तुझे नाश करे।"
    },
    {
      "verse": 60,
      "text": "तब सारी मण्डली ऊंचे शब्द से चिल्लाकर परमेश्वर की स्तुति करती है, जो उस पर भरोसा रखनेवालों को बचाता है।"
    },
    {
      "verse": 61,
      "text": "तब वे दोनों पुरनियों के विरूद्ध उठे, क्योंकि दानिरयेल ने उनको अपने ही मुंह से झूठी साक्षी दी थी।"
    },
    {
      "verse": 62,
      "text": "और मूसा की व्यवस्था के अनुसार उन्हों ने अपने पड़ोसी से बुरा बर्ताव किया; और उन्हों ने उन्हें मार डाला। और निदषों का लोहू उसी दिन बच गया।"
    },
    {
      "verse": 63,
      "text": "इसलिये कि उस में बेईमानी नहीं पाई गई, उन्हों ने अपनी बेटी शिमना के लिये, और अपने पति योममम के लिये परमेश्वर की स्तुति की।"
    },
    {
      "verse": 64,
      "text": "उस समय से लोगों की दृष्टि में दानिरयेल बड़ा नाम रखता था।"
    }
  ]
}