{
  "book": "ps",
  "chapter": 35,
  "verses": [
    {
      "verse": 1,
      "text": "हे यहोवा मेरे मुक मा लड़नेवालों से मेरा मुक मा लड़; जो मुझ से लड़ते हैं, उन से लड़।"
    },
    {
      "verse": 2,
      "text": "ढाल और भाला लेकर मेरी सहायता के लिये खड़ा हो।"
    },
    {
      "verse": 3,
      "text": "भाले को खींचकर मेरे सतानेवालों के विरूद्ध मार्ग रोक; मुझ से कह, मैं तेरा उद्धार हूं।"
    },
    {
      "verse": 4,
      "text": "जो मेरे प्राण के खोजी हैं, उनकी आशा टूटे और लज्जित हो जाए! जो मेरी हाति की कल्पना करते हैं, वे पीछे हटाए और लज्जित हों।"
    },
    {
      "verse": 5,
      "text": "वे वायु से उड़ाए हुए भूसे के समान हो जाएं, और यहोवा का दूत उनका पीछा करे।"
    },
    {
      "verse": 6,
      "text": "उनका मार्ग अन्धेरा और फिसल जाए, और यहोवा का दूत उन्हें खदेड़े।"
    },
    {
      "verse": 7,
      "text": "क्योंकि उन्हों ने व्यर्थ मेरे लिये अपना जाल गड़हे में छिपा रखा है, और व्यर्थ ही मेरे प्राण के लिये खोदा है।"
    },
    {
      "verse": 8,
      "text": "अचानक उस पर विपत्ति आ पड़े; और जो जाल उस ने छिपा रखा हो, वह अपने आप को पकड़ा जाए; उसी विनाश में वह गिर पड़े।।"
    },
    {
      "verse": 9,
      "text": "और मेरा प्राण यहोवा के कारण मगन होगा; वह उसके किए हुए उद्धार से मगन होगा।"
    },
    {
      "verse": 10,
      "text": "मेरी सब हडि्डयां कहेगा, हे यहोवा तेरे तुल्य कौन है? जो कंगाल और दरिद्र दोनों को लूटनेवाले से बचाता है, वह तेरे तुल्य है।"
    },
    {
      "verse": 11,
      "text": "झूठे साक्षी उठ खड़े हुए, उन्हों ने जो आज्ञा मैं ने नहीं पाई, उसे उन्हों ने मान लिया।"
    },
    {
      "verse": 12,
      "text": "उन्हों ने भलाई के बदले भलाई के बदले मुझ से बुराई की है।"
    },
    {
      "verse": 13,
      "text": "जब वे रोगी थे, तब मेरा वस्त्रा टाट पहिने था; मैं उपवास करके दीन हो गया, और मेरी प्रार्थना अपनी गोद में लौट गई।"
    },
    {
      "verse": 14,
      "text": "मैं मानो मानो अपने मित्रा वा भाई के समान बर्ताव करता था; जैसा उस की माता के लिये विलाप करती थी, वैसा ही मैं ने बहुत ही शोक किया।"
    },
    {
      "verse": 15,
      "text": "परन्तु जब मैं संकट में पड़ा, तब वे आनन्दित होकर इकट्ठे हुए, और नीच लोग भी मेरे विरूद्ध इकट्ठे हुए, और मैं न जानता था कि यह मेरा काम नहीं है, और वे मुझे फाड़ते हैं, और कुछ भी नहीं छोड़ते।"
    },
    {
      "verse": 16,
      "text": "ठट्ठा करनेवालों के साथ जेवनारों में ठट्ठा करते थे, और दांत पीसते थे।"
    },
    {
      "verse": 17,
      "text": "हे प्रभु तू कब तक देखता रहेगा? उनके विनाश से, मेरे प्राण को सिंहों से बचा ले!"
    },
    {
      "verse": 18,
      "text": "मैं बड़ी सभा में तेरा धन्यवाद करूंगा; मैं बहुत सी जातियों के बीच तेरा धन्यवाद करूंगा।"
    },
    {
      "verse": 19,
      "text": "मेरे झूठ बोलनेवाले शत्रु मेरे विरूद्ध आनन्द न करें, और जो अकारण मुझ से बैर रखते हैं, वे नैन से सैन न करें।"
    },
    {
      "verse": 20,
      "text": "क्योंकि वे शान्ति की बातें नहीं बोलते, परन्तु देश में जो चुपचाप रहते हैं, उनके विरूद्ध छल की बातें गढ़ते हैं।"
    },
    {
      "verse": 21,
      "text": "वरन उन्हों ने मेरे विरूद्ध मुंह खोलकर कहा, आहा, आहा, हम ने अपनी आंखों से देखा है।"
    },
    {
      "verse": 22,
      "text": "हे यहोवा, तू ने यह देखा है; चुप न रह, हे प्रभु, मुझ से दूर न रह!"
    },
    {
      "verse": 23,
      "text": "हे मेरे परमेश्वर, हे मेरे प्रभु, मेरे न्याय के लिये जाग!"
    },
    {
      "verse": 24,
      "text": "हे मेरे परमेश्वर यहोवा, अपने धर्म के अनुसार मेरा न्याय चुका; और वे मेरे विषय आनन्द न करें।"
    },
    {
      "verse": 25,
      "text": "वे अपने मन में यह न कहने पाएं, कि हाय, हम तो चाहते हैं; वे यह न कहें, कि हम ने उसे निगल लिया है।"
    },
    {
      "verse": 26,
      "text": "जो मेरी हानि के कारण आनन्द करते हैं, वे लज्जित हों, और एक साथ लज्जित हों; जो मेरे विरूद्ध बड़ाई मारते हैं, वे लज्जा और अनादर के वस्त्रा पहिने रहें।"
    },
    {
      "verse": 27,
      "text": "जो मेरे धर्म से प्रसन्न होते हैं, वे जयजयकार करें, और जयजयकार करें! और निरन्तर करते रहें, यहोवा की बड़ाई हो, जो अपने दास के कुशल से प्रसन्न होता है!"
    },
    {
      "verse": 28,
      "text": "और मेरी जीभ तेरे धर्म की चर्चा और दिन भर तेरी स्तुति की जाएगी।।"
    }
  ]
}