{
  "book": "mark",
  "chapter": 4,
  "verses": [
    {
      "verse": 1,
      "text": "और वह फिर झील के किनारे उपदेश देने लगा, और उसके पास एक बड़ी भीड़ इकट्ठी हुई, कि नाव पर चढ़कर झील में बैठ गया; और सारी भीड़ समुद्र के किनारे थी।"
    },
    {
      "verse": 2,
      "text": "और वह उन्हें दृष्टान्तों में बहुत सी बातें सिखाने लगा, और अपने उपदेश में उन से कहा।"
    },
    {
      "verse": 3,
      "text": "सुनो, देखो, एक बीज बोने के लिये निकला।"
    },
    {
      "verse": 4,
      "text": "बोते समय कुछ तो मार्ग के किनारे गिरा, और आकाश के पक्षी आकर उसे भस्म कर डाला।"
    },
    {
      "verse": 5,
      "text": "और कुछ चट्टान पर गिरा, जहां बहुत मिट्टी न थी; और तुरन्त उग आए, क्योंकि पृथ्वी की गहराई कुछ न थी।"
    },
    {
      "verse": 6,
      "text": "जब सूर्य निकला, तो जल गया, और जड़ न पकड़ने के कारण सूख गया।"
    },
    {
      "verse": 7,
      "text": "और कुछ झाड़ियों में गिरा, और झाड़ियों ने बढ़कर उसे दबा लिया, और वह फल न लाया।"
    },
    {
      "verse": 8,
      "text": "और कुछ अच्छी भूमि पर गिरा, और फलवन्त हुआ, और कोई तीस गुणा, कोई साठ, कोई सौ गुणा फल लाया।"
    },
    {
      "verse": 9,
      "text": "उस ने उन से कहा; जिस के कान हों वह सुन ले।"
    },
    {
      "verse": 10,
      "text": "जब वह अकेला था, तो जो उसके आस पास थे उन्हों ने उस से यह दृष्टान्त पूछा।"
    },
    {
      "verse": 11,
      "text": "उस ने उन से कहा; तुम्हें परमेश्वर के राज्य के भेद की समझ दी गई है, परन्तु बाहरवालों के लिये ये सब बातें दृष्टान्तों में होती हैं।"
    },
    {
      "verse": 12,
      "text": "जिस से वे देखते और देखते भी रहें, और सुनते हुए भी न समझें; ऐसा न हो कि वे फिरकर अपने पाप क्षमा किए जाएं।"
    },
    {
      "verse": 13,
      "text": "उस ने उन से कहा; क्या तुम यह दृष्टान्त नहीं जानते? फिर तुम सब दृष्टान्तों को क्योंकर जानते हो?"
    },
    {
      "verse": 14,
      "text": "बीज बोनेवाला वचन को बोता है ।"
    },
    {
      "verse": 15,
      "text": "वे मार्ग में हैं, जहां वचन बोया जाता है: परन्तु जब उन्हों ने सुना, तो शैतान तुरन्त आकर वचन को जो उन के मन में बोया गया था, उठा ले जाता है।"
    },
    {
      "verse": 16,
      "text": "और वैसे ही वे भी हैं, जो चट्टान पर बोए जाते हैं; और वचन को सुनकर तुरन्त आनन्द से ग्रहण करते हैं।"
    },
    {
      "verse": 17,
      "text": "और अपने में जड़ न खाना; और थोड़े दिन के लिये धीरज धरता है: उसके बाद जब वचन के कारण क्लेश या उपद्रव होता है, तो तुरन्त वे ठोकर खाते हैं।"
    },
    {
      "verse": 18,
      "text": "ये वे हैं, जो झाड़ियों में बोए गए, और वचन को सुनते हैं।"
    },
    {
      "verse": 19,
      "text": "और इस संसार की चिन्ता, और धन का धोखा, और और औरों की लालसाओं में फंसते हैं, और वचन को दबाते हैं, और निष्फल हो जाते हैं।"
    },
    {
      "verse": 20,
      "text": "और जो अच्छी भूमि में बोए गए ये वे हैं, जो वचन सुनकर ग्रहण करते, और फल लाते हैं, कोई तीस गुणा, कोई साठ गुणा, कोई साठ गुणा, और कोई सौ गुणा।"
    },
    {
      "verse": 21,
      "text": "उस ने उन से कहा; क्या दीपक झाड़ी के नीचे, या खाट के नीचे रखा गया है? क्या दीवट पर रखने के लिये नहीं?"
    },
    {
      "verse": 22,
      "text": "क्योंकि कोई वस्तु छिपी नहीं, जो प्रगट न हो; और न कुछ गुप्त था, परन्तु इसलिये कि प्रगट हो जाए।"
    },
    {
      "verse": 23,
      "text": "यदि किसी के सुनने के कान हों, तो सुन ले।"
    },
    {
      "verse": 24,
      "text": "उस ने उन से कहा; चौकस रहो, कि क्या सुनते हो? जिस नाप से तुम नापते हो, उसी से तुम्हारे लिये भी नापा जाएगा; और जो तुम्हारी सुनते हैं, वह अधिक दिया जाएगा।"
    },
    {
      "verse": 25,
      "text": "क्योंकि जिस के पास है, उसे दिया जाएगा; और जिस के पास नहीं है, उस से वह भी जो उसके पास है, ले लिया जाएगा।"
    },
    {
      "verse": 26,
      "text": "उस ने कहा, परमेश्वर का राज्य ऐसा है जैसा कोई मनुष्य भूमि पर बीज बो दे।"
    },
    {
      "verse": 27,
      "text": "और रात को सोते, और दिन बढ़ता जाए, और बीज उगते और बढ़ता जाए, तो वह नहीं जानता कि कैसा कैसा है।"
    },
    {
      "verse": 28,
      "text": "क्योंकि पृथ्वी आप ही से फल लाती है; पहिले अंकुर, तब कान, और कान कान, और कान उसी के सुनने के बाद।"
    },
    {
      "verse": 29,
      "text": "परन्तु जब फल उत्पन्न होता है, तो तुरन्त हंसुआ लगाता है, क्योंकि कटनी आ पहुंची है।"
    },
    {
      "verse": 30,
      "text": "उस ने कहा, हम परमेश्वर के राज्य की उपमा किस से दें, और किस से उस की उपमा दें?"
    },
    {
      "verse": 31,
      "text": "वह राई के दाने के समान है, जो भूमि में बोया जाता है, और पृथ्वी के सब बीजों से छोटा है।"
    },
    {
      "verse": 32,
      "text": "परन्तु जब बोया जाता है, तो वह उगकर सब साग पात से बड़ा होता है, और बड़ी डालियां तोड़ देता है, और आकाश के पक्षी उसकी छाया में बसेरा करते हैं।"
    },
    {
      "verse": 33,
      "text": "और उस ने बहुत से दृष्टान्तों से उन से ऐसा ही वचन कहा, जैसा वे सुन सकते थे।"
    },
    {
      "verse": 34,
      "text": "परन्तु उस ने बिना दृष्टान्त उन से बातें न की; और जब वे एकान्त में थे, तो सब कुछ अपने चेलों को बता दिया।"
    },
    {
      "verse": 35,
      "text": "उसी दिन जब सांझ हुई, तो उस ने उन से कहा, आओ, हम पार चलें।"
    },
    {
      "verse": 36,
      "text": "और उन्हों ने भीड़ को विदा किया, और जैसा वह जहाज पर था, वैसा ही उसे ले गए: और उसके साथ और भी नावें थीं।"
    },
    {
      "verse": 37,
      "text": "तब एक बड़ी आंधी उठी, और लहरें नाव पर यहां तक लगीं, कि वह अब पूरी हो गई।"
    },
    {
      "verse": 38,
      "text": "और वह नाव की छोर पर था, जो तकिया में सो रहा था, और वे उसे जगाकर उस से कहने लगे, हे गुरू, क्या तुझे चिन्ता नहीं, कि हम नाश हों?"
    },
    {
      "verse": 39,
      "text": "तब उस ने उठकर आन्धी को डांटा, और समुद्र से कहा, कुशल बना रह; और आन्धी थम गई, और बड़ा चैन हो गया।"
    },
    {
      "verse": 40,
      "text": "उस ने उन से कहा; तुम क्यों इस बात से डरते हो? फिर तुम क्यों विश्वास नहीं करते?"
    },
    {
      "verse": 41,
      "text": "और वे बहुत ही डर गए, और आपस में कहने लगे, यह कैसा मनुष्य है, कि आन्धी और पानी भी उस की आज्ञा मानते हैं?"
    }
  ]
}