{
  "book": "jdt",
  "chapter": 7,
  "verses": [
    {
      "verse": 1,
      "text": "और दूसरे दिन होलोनियों ने अपनी सारी सेना और अपनी सारी सेना को जो उसका भाग लेने को आई थी आज्ञा दी, कि वे अपने छावनी को बेतसूरिया के साम्हने से दूर करें, और पहाड़ी देश की चढ़ाई को पार करके इस्राएलियों से युद्ध करें।"
    },
    {
      "verse": 2,
      "text": "तब उन के बलवन्त पुरूषों ने अपनी छावनी हटाई, और युद्ध के पुरूषों की सेना एक लाख सत्तर हजार प्यादों और बारह हजार सवार, और सामान के पास, और उन में से और भी बहुत बड़ी भीड़ थी।"
    },
    {
      "verse": 3,
      "text": "और वे उस तराई में बेथेल के पास, और सोते के पास की तराई में डेरे डाले हुए थे, और बेथैम तक, और बेथेल से होते हुए, जो ऐलमोन के साम्हने है, हल्मोन तक फैल गए।"
    },
    {
      "verse": 4,
      "text": "जब इस्राएलियों ने उन की भीड़ को देखा, तब वे बहुत घबरा गए, और अपने अपने पड़ोसी से कहने लगे, ये लोग अब पृथ्वी के मुंह को चाटेंगे; क्योंकि न तो ऊंचे पहाड़ों, न पहाड़ियों, न पहाड़ियों, न उनके तौल का भार उठाया जा सकता है।"
    },
    {
      "verse": 5,
      "text": "तब हर एक ने अपने हथियार लिए, और जब वे अपने गुम्मटों पर आग लगाकर फूंकते थे, तब वे रात भर वहीं रहे।"
    },
    {
      "verse": 6,
      "text": "परन्तु दूसरे दिन होलोनियों ने अपने सब सवार इस्राएलियों के साम्हने जो बेतहेमया में थे,"
    },
    {
      "verse": 7,
      "text": "और उस तराई को देखा, और अपने जल के सोतों के पास जाकर उन्हें ले गया, और उनके ऊपर योद्धाओं की चौकी बैठा दी, और अपने लोगों की ओर अपने को ले गया।"
    },
    {
      "verse": 8,
      "text": "तब एसावियों के सब प्रधानों और मोआबियों और समुद्रतीर के प्रधानों ने उसके पास आकर कहा,"
    },
    {
      "verse": 9,
      "text": "हमारे प्रभु को यह वचन सुनने दे, कि तेरी सेना में कुछ भी मिट न जाए।"
    },
    {
      "verse": 10,
      "text": "क्योंकि इस्त्राएली अपने भालों पर भरोसा नहीं रखते, वरन पहाड़ों की चोटी पर रहते हैं, क्योंकि उनके पहाड़ों की चोटियों पर चढ़ने में आसान नहीं।"
    },
    {
      "verse": 11,
      "text": "इसलिये अब हे मेरे प्रभु, युद्ध में उन से न लड़ो, और तेरी प्रजा में से कोई भी नाश न होगा।"
    },
    {
      "verse": 12,
      "text": "अपनी छावनी में रह, और अपनी सेना के सब पुरूषों की रक्षा कर; और तेरे दास जल के सोते को अपने हाथ में कर लें, जो पहाड़ के तल से निकलता है।"
    },
    {
      "verse": 13,
      "text": "क्योंकि वहां के सब रहनेवालों को उनका पानी प्यास होगी; और वे अपने नगर को मार डालेंगे, और हम अपने लोगों समेत पहाड़ों की चोटियों पर चढ़ जाएंगे, और छावनी लगाकर उनको घात करेंगे कि कोई नगर से बाहर जाने न पाएगा।"
    },
    {
      "verse": 14,
      "text": "तब वे और उनकी स्त्रियां और बच्चे आग से भस्म हो जाएंगे, और तलवार से उन पर चढ़ाई करेंगे, और जहां वे रहते हैं वहां वे सड़कों में गिराए जाएंगे।"
    },
    {
      "verse": 15,
      "text": "तू उन्हें ऐसी बुराई का बदला देना; क्योंकि उन्हों ने बलवा किया, और अपने जन को मेल- मिलाप से न पाया।"
    },
    {
      "verse": 16,
      "text": "और ये बातें होलोन और उसके सब कर्मचारी प्रसन्न हुए, और जैसा वे कह रहे थे वैसा ही करने के लिये उस ने नियुक्‍त किया।"
    },
    {
      "verse": 17,
      "text": "तब अम्मोनियों की छावनी चली, और उनके संग पांच हजार अश्शूरी चले, और तराई में डेरे खड़े किए, और इस्त्राएलियों के जल और जल के सोते ले लिए।"
    },
    {
      "verse": 18,
      "text": "तब एसावियों ने अम्मोनियों के संग जाकर दोथैम के साम्हने पहाड़ी देश में छावनी डाली; और उन्हों ने उन में से कितनों को दक्खिन, और पूर्व की ओर, जो शिल्लेल नाम नाले के पास है, और अश्शूरियों की सेना के और नीचे की तराई में की सारी छावनी को ढांप दिया; और उनके डेरे बहुत बड़े बड़े डेरे खड़े किए गए।"
    },
    {
      "verse": 19,
      "text": "तब इस्राएलियों ने अपने परमेश्वर की दोहाई दी, क्योंकि उनका मन टूट गया था, क्योंकि उनके सब शत्रुओं ने उन्हें घेर लिया था, और उनके बीच से निकल जाने का कोई मार्ग न था।"
    },
    {
      "verse": 20,
      "text": "इस प्रकार गदही के सब दल के लोग, और उनके सरदार, रथ, और सवार, चार सौ तीस दिन तक रहे, यहां तक कि उनके सब पात्रा बेतूलिया के सब जोखिमों में पड़ गए।"
    },
    {
      "verse": 21,
      "text": "और हौद खाली हो गए थे, और उन्हें एक दिन के लिये पानी न पिलाया गया था, क्योंकि उन्हों ने उन्हें थोड़ा पानी पिलाया था।"
    },
    {
      "verse": 22,
      "text": "इस कारण उनके लड़के- लड़कियाँ प्यास के मारे निराश हो गई, और नगर के चौकों और फाटकों के किनारे गिरा, और उन में कुछ बल न रहा।"
    },
    {
      "verse": 23,
      "text": "तब सब लोग ओशीया और नगर के प्रधानों के पास इकट्ठे होकर ऊंचे शब्द से पुकारकर सब पुरनियों से कहने लगे,"
    },
    {
      "verse": 24,
      "text": "परमेश्वर हमारे और तुम्हारे बीच न्याय करे; क्योंकि तुम ने हम से बड़ी चोट खाई है, इसलिये कि तुम ने गदहियों की सन्तान से शान्ति की माँग नहीं की।"
    },
    {
      "verse": 25,
      "text": "क्योंकि अब हमारा कोई सहायक नहीं, परन्तु परमेश्वर ने हमें उनके हाथ में कर दिया है, कि हम प्यास और सत्यानाश से उनके साम्हने दब जाएं।"
    },
    {
      "verse": 26,
      "text": "इसलिये अब तुम को बुला लो, और सारे नगर को ले जाओ, कि होलोनियों और उसकी सारी सेना को लूट लो।"
    },
    {
      "verse": 27,
      "text": "क्योंकि हमारे लिये इस से भला है कि हम प्यासी मर जाएं; क्योंकि हम उसके दास होंगे, कि हम जीवित रहें, और अपने बालकों की मृत्यु को न देखें, और न हमारी स्त्रियां, और न हमारी सन्तान मर जाएं।"
    },
    {
      "verse": 28,
      "text": "हम आकाश और पृथ्वी और हमारे परमेश्वर और हमारे पूर्वजों के परमेश्वर की गवाही देते हैं, जो हमें हमारे पापों और हमारे पुरखाओं के पापों के अनुसार दण्ड देता है, कि जैसा हम ने कहा था, वैसा ही वह आज तक नहीं करता।"
    },
    {
      "verse": 29,
      "text": "तब कलीसिया के बीच में एक मन होकर बहुत रो पड़ा, और बड़े शब्द से प्रभु की दोहाई दी।"
    },
    {
      "verse": 30,
      "text": "तब हे भाइयो, हे भाइयो, ढाढ़स बान्धों, हम पांच दिन तक धीरज रखें, जिस में हमारा परमेश्वर प्रभु हमारी ओर अपनी दया करे, क्योंकि वह हमें पूरी रीति से न छोड़ेगा।"
    },
    {
      "verse": 31,
      "text": "और यदि ये दिन पूरे हों, और हमारी सहायता न करूंगा, तो मैं तेरे वचन के अनुसार करूंगा।"
    },
    {
      "verse": 32,
      "text": "और उस ने लोगों को अलग अलग किया; और वे अपने नगर की शहरपनाह और गुम्मटों के पास गए, और स्त्रियों और लड़केबालों को उनके घरों में भेज दिया; और वे नगर में बहुत ही नीच हो गई थीं।"
    }
  ]
}